{
  "generator-jhipster": {
    "promptValues": {
      "packageName": "com.viettel.vn",
      "nativeLanguage": "en"
    },
    "jhipsterVersion": "6.4.1",
    "applicationType": "monolith",
    "baseName": "Viettel",
    "packageName": "com.viettel.vn",
    "packageFolder": "com/viettel/vn",
    "serverPort": "18080",
    "authenticationType": "jwt",
    "cacheProvider": "ehcache",
    "enableHibernateCache": true,
    "websocket": false,
    "databaseType": "sql",
    "devDatabaseType": "mssql",
    "prodDatabaseType": "mssql",
    "searchEngine": false,
    "messageBroker": false,
    "serviceDiscoveryType": "eureka",
    "buildTool": "maven",
    "enableSwaggerCodegen": false,
    "jwtSecretKey": "OTMyYzBlNjI2Yjg2NWNjNjE2MmNmNGFiZGJjNjNhMTdmNjZjYmRkYjhkZWFkYmM5YTMzZTBhMmZmOTQxM2EwOWNlMmFjMTYzZTNmOGM5NzA0NDgzOGMyN2VjMTFkMGYzMjMyMGM5NDNkOWM2YTliMWM3NDY4NzRjODM4ZWQ1MGE=",
    "embeddableLaunchScript": false,
    "useSass": true,
    "clientPackageManager": "npm",
    "clientFramework": "angularX",
    "clientTheme": "none",
    "clientThemeVariant": "",
    "testFrameworks": ["protractor"],
    "jhiPrefix": "jhi",
    "entitySuffix": "",
    "dtoSuffix": "DTO",
    "otherModules": [],
    "enableTranslation": true,
    "nativeLanguage": "en",
    "languages": ["en", "vi"],
    "blueprints": []
  }
}
